{"name":"build-javascript","namedChunkGroups":{"polyfill":{"name":"polyfill","assets":[{"name":"webpack-runtime-08873500c0e4970ea87f.js","size":4548},{"name":"polyfill-d2bcbad9d6317bccf982.js","size":85832}],"filteredAssets":0,"assetsSize":90380,"filteredAuxiliaryAssets":2,"auxiliaryAssetsSize":225780},"app":{"name":"app","assets":[{"name":"webpack-runtime-08873500c0e4970ea87f.js","size":4548},{"name":"framework-b28104f38a9d6acde6cc.js","size":140536},{"name":"app-0b9c3175f125f598f284.js","size":120443}],"filteredAssets":0,"assetsSize":265527,"filteredAuxiliaryAssets":3,"auxiliaryAssetsSize":864954},"component---src-pages-404-js":{"name":"component---src-pages-404-js","assets":[{"name":"styles.7d743f092affc378d1a6.css","size":2506},{"name":"commons-4ac478411e8289ae3f90.js","size":16316},{"name":"component---src-pages-404-js-0a228cda15d5cb133776.js","size":413}],"filteredAssets":0,"assetsSize":19235,"filteredAuxiliaryAssets":2,"auxiliaryAssetsSize":68497},"component---src-pages-blog-js":{"name":"component---src-pages-blog-js","assets":[{"name":"styles.7d743f092affc378d1a6.css","size":2506},{"name":"commons-4ac478411e8289ae3f90.js","size":16316},{"name":"component---src-pages-blog-js-fab3eda18ad953837ce2.js","size":791}],"filteredAssets":0,"assetsSize":19613,"filteredAuxiliaryAssets":2,"auxiliaryAssetsSize":69939},"component---src-pages-index-js":{"name":"component---src-pages-index-js","assets":[{"name":"styles.7d743f092affc378d1a6.css","size":2506},{"name":"commons-4ac478411e8289ae3f90.js","size":16316},{"name":"component---src-pages-index-js-24eb2983d6f857322ee8.js","size":1315}],"filteredAssets":0,"assetsSize":20137,"filteredAuxiliaryAssets":2,"auxiliaryAssetsSize":69543},"component---src-pages-search-js":{"name":"component---src-pages-search-js","assets":[{"name":"styles.7d743f092affc378d1a6.css","size":2506},{"name":"commons-4ac478411e8289ae3f90.js","size":16316},{"name":"component---src-pages-search-js-e07dd6a2a72cef9ea50e.js","size":1302}],"filteredAssets":0,"assetsSize":20124,"filteredAuxiliaryAssets":2,"auxiliaryAssetsSize":71110},"component---src-templates-post-js":{"name":"component---src-templates-post-js","assets":[{"name":"styles.7d743f092affc378d1a6.css","size":2506},{"name":"commons-4ac478411e8289ae3f90.js","size":16316},{"name":"component---src-templates-post-js-2ee8843b98480e6b3515.js","size":840}],"filteredAssets":0,"assetsSize":19662,"filteredAuxiliaryAssets":2,"auxiliaryAssetsSize":69757}},"assetsByChunkName":{"polyfill":["webpack-runtime-08873500c0e4970ea87f.js","polyfill-d2bcbad9d6317bccf982.js"],"app":["webpack-runtime-08873500c0e4970ea87f.js","framework-b28104f38a9d6acde6cc.js","app-0b9c3175f125f598f284.js"],"component---src-pages-404-js":["styles.7d743f092affc378d1a6.css","commons-4ac478411e8289ae3f90.js","component---src-pages-404-js-0a228cda15d5cb133776.js"],"component---src-pages-blog-js":["styles.7d743f092affc378d1a6.css","commons-4ac478411e8289ae3f90.js","component---src-pages-blog-js-fab3eda18ad953837ce2.js"],"component---src-pages-index-js":["styles.7d743f092affc378d1a6.css","commons-4ac478411e8289ae3f90.js","component---src-pages-index-js-24eb2983d6f857322ee8.js"],"component---src-pages-search-js":["styles.7d743f092affc378d1a6.css","commons-4ac478411e8289ae3f90.js","component---src-pages-search-js-e07dd6a2a72cef9ea50e.js"],"component---src-templates-post-js":["styles.7d743f092affc378d1a6.css","commons-4ac478411e8289ae3f90.js","component---src-templates-post-js-2ee8843b98480e6b3515.js"]},"childAssetsByChunkName":{}}